{
  "version": "4.0",
  "updated": "2026-05-11",
  "notes": "Phase 6: Conditional weight smoothing to avoid flash-trade triggers",
  "stage1": {
    "revenue_momentum": 0.20,
    "profitability": 0.25,
    "valuation": 0.15,
    "institutional_flow": 0.20,
    "technical_momentum": 0.20
  },
  "stage2": {
    "revenue_growth": 0.20,
    "margin_stability": 0.15,
    "roe_level": 0.15,
    "cash_flow_quality": 0.15,
    "balance_sheet": 0.15,
    "earnings_surprise": 0.10,
    "management": 0.10
  },
  "regime_weights": {
    "normal": {
      "revenue_momentum": 0.25,
      "profitability": 0.20,
      "valuation": 0.10,
      "institutional_flow": 0.25,
      "technical_momentum": 0.20
    },
    "caution": {
      "revenue_momentum": 0.20,
      "profitability": 0.20,
      "valuation": 0.20,
      "institutional_flow": 0.20,
      "technical_momentum": 0.20
    },
    "stress": {
      "revenue_momentum": 0.15,
      "profitability": 0.25,
      "valuation": 0.25,
      "institutional_flow": 0.20,
      "technical_momentum": 0.15
    },
    "crisis": {
      "revenue_momentum": 0.10,
      "profitability": 0.25,
      "valuation": 0.30,
      "institutional_flow": 0.20,
      "technical_momentum": 0.15
    },
    "black_swan": null
  },
  "smoothing": {
    "max_weight_change_pct": 0.05,
    "description": "Phase 6: Limit per-day weight changes to 5% to avoid flash-trade triggers"
  }
}
